odoo/addons/sale_order_currency_rate/README.rst
odoo/addons/sale_order_currency_rate/__init__.py
odoo/addons/sale_order_currency_rate/__manifest__.py
odoo/addons/sale_order_currency_rate/data/decimal_precision_data.xml
odoo/addons/sale_order_currency_rate/i18n/es.po
odoo/addons/sale_order_currency_rate/i18n/es_MX.po
odoo/addons/sale_order_currency_rate/i18n/it.po
odoo/addons/sale_order_currency_rate/i18n/sale_order_currency_rate.pot
odoo/addons/sale_order_currency_rate/models/__init__.py
odoo/addons/sale_order_currency_rate/models/res_company.py
odoo/addons/sale_order_currency_rate/models/res_config_settings.py
odoo/addons/sale_order_currency_rate/models/sale_order.py
odoo/addons/sale_order_currency_rate/readme/CONTRIBUTORS.rst
odoo/addons/sale_order_currency_rate/readme/DESCRIPTION.rst
odoo/addons/sale_order_currency_rate/readme/USAGE.rst
odoo/addons/sale_order_currency_rate/static/description/icon.png
odoo/addons/sale_order_currency_rate/static/description/index.html
odoo/addons/sale_order_currency_rate/views/res_config_settings.xml
odoo/addons/sale_order_currency_rate/views/sale_order.xml
odoo_addon_sale_order_currency_rate-16.0.1.0.0.10.dist-info/METADATA
odoo_addon_sale_order_currency_rate-16.0.1.0.0.10.dist-info/WHEEL
odoo_addon_sale_order_currency_rate-16.0.1.0.0.10.dist-info/top_level.txt
odoo_addon_sale_order_currency_rate-16.0.1.0.0.10.dist-info/RECORD
